{
  "name": "AMOLED anime theme",
  "description": "AMOLED Rem theme",
  "authors": [
    {
      "name": "wiwiichan",
      "id": "725075745671479296"
    }
  ],
  "semanticColors": {
    "BACKGROUND_TERTIARY": ["#111111"],
    "BACKGROUND_ACCENT": ["#1a1a1a"],
    "BACKGROUND_SECONDARY": ["#111111"],
    "BACKGROUND_MODIFIER_ACCENT": ["#1a1a1a"],
    "DIVIDER_STRONG": ["#1a1a1a"],
    "DIVIDER_SUBTLE": ["#1a1a1a"],
    "BORDER_SUBTLE": ["#1a1a1a"],
    "SPINE_DEFAULT": ["#1a1a1a"],
    "SPOILER_HIDDEN_BACKGROUND": ["#1a1a1a"],
    "SPOILER_REVEALED_BACKGROUND": ["#1a1a1a"],
    "STAGE_CARD_PILL_BG": ["#111111"],
    "STATUS_DANGER": ["#111111"],
    "STATUS_DANGER_BACKGROUND": ["#111111"],
    "STATUS_DANGER_TEXT": ["#FFFFFF"],
    "STATUS_DND": ["#ff6161"],
    "STATUS_IDLE": ["#ffbc5b"],
    "STATUS_OFFLINE": ["#202020"],
    "STATUS_ONLINE": ["#48bc46"],
    "STATUS_POSITIVE": ["#111111"],
    "STATUS_POSITIVE_BACKGROUND": ["#111111"],
    "STATUS_POSITIVE_TEXT": ["#FFFFFF"],
    "STATUS_SPEAKING": ["#111111"],
    "STATUS_WARNING": ["#FFFFFF"],
    "STATUS_WARNING_BACKGROUND": ["#111111"],
    "STATUS_WARNING_TEXT": ["#FFFFFF"],
    "TEXT_PRIMARY": ["#FFFFFF"],
    "TEXT_SECONDARY": ["#FFFFFF"],
    "TEXT_NORMAL": ["#FFFFFF"],
    "TEXT_MUTED": ["#9a9a9a"],
    "TEXT_LINK": ["#009AFF"],
    "THREAD_CHANNEL_SPINE": ["#FFFFFF"],
    "TOAST_BG": ["#111111"],
    "TYPING_INDICATOR_BG": ["#111111"],
    "USER_PROFILE_HEADER_OVERFLOW_BACKGROUND": ["#111111"],
    "VOICE_VIDEO_VIDEO_TILE_BACKGROUND": ["#111111"],
    "WHITE": ["#FFFFFF"],
    "SCROLLBAR_THIN_TRACK": ["#111111"],
    "SCROLLBAR_AUTO_TRACK": ["#111111"],
    "REDESIGN_BUTTON_TERTIARY_BACKGROUND": ["#111111"],
    "REDESIGN_CHAT_INPUT_BACKGROUND": ["#111111"],
    "CHAT_INPUT_CONTAINER_BACKGROUND": ["#111111"],
    "MENTION_BADGE": ["#ff6161"],
    "REDESIGN_MENTION_BADGE": ["#ff6161"]
  },

  "background": {
    "url": "https://i.postimg.cc/HL7z5R0Q/IMG-8527.jpg",
    "blur": 0.1,
    "alpha": 0.35,
    "size": "cover",
    "position": "center"
  },

  "plus": {
    "version": "0",
    "iconpack": "solar"
  },
  "spec": 2
}
